ZenBand/APP_BODY.py
ZenBand/Band_Gaps.py
ZenBand/Device.py
ZenBand/Get_Data.py
ZenBand/PWEM_model_fields.py
ZenBand/PWEM_model_v2.py
ZenBand/Params.py
ZenBand/__init__.py
ZenBand/create_fig.py
ZenBand/main_bands.py
ZenBand/main_fields.py
ZenBand/main_gif.py
zenband-0.1.3.dist-info/METADATA
zenband-0.1.3.dist-info/WHEEL
zenband-0.1.3.dist-info/entry_points.txt
zenband-0.1.3.dist-info/top_level.txt
zenband-0.1.3.dist-info/RECORD
