Metadata-Version: 2.4
Name: zenband
Version: 0.1.3
Requires-Dist: customtkinter
Requires-Dist: tqdm
Requires-Dist: imageio
Dynamic: description
Dynamic: description-content-type
Dynamic: requires-dist
